tabata/Workbook.py
Tabata-0.1.1.dist-info/LICENSE
Tabata-0.1.1.dist-info/METADATA
Tabata-0.1.1.dist-info/WHEEL
Tabata-0.1.1.dist-info/top_level.txt
Tabata-0.1.1.dist-info/RECORD
